gempaterkini/__init__.py
Indonesia_earthquakeliveinfo-1.0.dist-info/LICENSE
Indonesia_earthquakeliveinfo-1.0.dist-info/METADATA
Indonesia_earthquakeliveinfo-1.0.dist-info/WHEEL
Indonesia_earthquakeliveinfo-1.0.dist-info/setup1.py
Indonesia_earthquakeliveinfo-1.0.dist-info/top_level.txt
Indonesia_earthquakeliveinfo-1.0.dist-info/RECORD
