Metadata-Version: 2.1
Name: Indonesia-earthquakeliveinfo
Version: 1.0
Summary: Package content with beautifulsoup4 and requests, from JSON can be used on mobile & web applications
Author-email: Muchamad Faiz <muchamadfaiz@gmail.com>
License: GNU GENERAL PUBLIC LICENSE
Project-URL: Homepage, https://github.com/muchamadfaiz/latest-indonesia-earthquake
Classifier: Programming Language :: Python :: 3
Classifier: License :: OSI Approved :: GNU General Public License v3 (GPLv3)
Classifier: Operating System :: OS Independent
Classifier: Development Status :: 5 - Production/Stable
Requires-Python: >=3.7
License-File: LICENSE
